CyStack.cpython-38-darwin.so
CyStack-0.1.5.dist-info/METADATA
CyStack-0.1.5.dist-info/WHEEL
CyStack-0.1.5.dist-info/top_level.txt
CyStack-0.1.5.dist-info/RECORD
