Metadata-Version: 2.1
Name: CyStack
Version: 0.1.5
Summary: Custom Stack & Queue
Home-page: UNKNOWN
Author: Robert Sharp
Author-email: webmaster@sharpdesigndigital.com
License: Free for non-commercial use
Keywords: Stack,Queue
Platform: UNKNOWN
Classifier: Development Status :: 4 - Beta
Classifier: Programming Language :: Python :: 3.7
Classifier: Programming Language :: Cython
Classifier: Programming Language :: C++
Requires-Python: >=3.6
